server.py
mseep_tripo_mcp-0.1.6.dist-info/licenses/LICENSE
mseep_tripo_mcp-0.1.6.dist-info/METADATA
mseep_tripo_mcp-0.1.6.dist-info/WHEEL
mseep_tripo_mcp-0.1.6.dist-info/entry_points.txt
mseep_tripo_mcp-0.1.6.dist-info/top_level.txt
mseep_tripo_mcp-0.1.6.dist-info/RECORD
